{
    "title": "โลกที่แตกต่าง",
    "description": "นิทรรศการเดี่ยวครั้งแรกของศิลปินที่ได้รับแรงบันดาลใจจากธรรมชาติและสิ่งแวดล้อมรอบตัว ซึ่งเต็มไปด้วยสิ่งที่น่าสนใจให้ค้นหาและเรียนรู้ ศิลปินถ่ายทอดจินตนาการผ่านผลงานจิตรกรรมในหลากหลายรูปแบบ สะท้อนเรื่องราวการดำเนินชีวิตของมนุษย์และความสัมพันธ์กับสภาวะแวดล้อมในปัจจุบัน",
    "start_date": "5 มีนาคม 2025",
    "end_date": "30 มีนาคม 2025",
    "categories": [
        "Art & Design"
    ],
    "event_slot_time": "10:00-20:00",
    "location": "หอศิลปวัฒนธรรมแห่งกรุงเทพมหานคร",
    "url": "https://www.bangkokartcity.org/th/discover-detail/the-different-world",
    "ticket": "ไม่มีค่าเข้าชม",
    "ticket_price": null,
    "cover_picture": "https://framerusercontent.com/images/6bNlHlpiOva0l5ETjM36LgZdWQ.jpeg",
    "reliability_score": 2,
    "timestamp": "2025-03-29 17:10:46",
    "status": "ongoing"
}