{
    "title": "สุวรรณภูมิ",
    "description": "‘สุวรรณภูมิ’ คือดินแดนอันมั่งคั่งที่ถูกจารึกไว้ในประวัติศาสตร์ สัญลักษณ์ของการหลอมรวมระหว่างความคิดจากโลกตะวันตกและตะวันออก ซึ่งเป็นจุดเชื่อมต่อของศิลปะ วัฒนธรรม และแนวคิดในการดำเนินชีวิต ที่ผสานกันอย่างกลมกลืนผ่านกาลเวลา นิทรรศการ “สุวรรณภูมิ” นำเสนอศิลปะที่สะท้อนถึงสองกระแสความคิดอันแตกต่าง ระหว่างโลกตะวันตกที่เชื่อในพลังของมนุษย์ที่สามารถเอาชนะธรรมชาติและควบคุมทุกสรรพสิ่งได้ด้วยความรู้และเหตุผล กับโลกตะวันออกยึดถือเชื่อมั่นในวิถีการดำเนินชีวิตด้วยจิตวิญญาณและการอยู่ร่วมกับธรรมชาติอย่างสมดุล มนุษย์ สัตว์ ป่าไม้ และสายน้ำล้วนเกื้อกูลกันอย่างลึกซึ้ง จนกลายเป็นรากฐานของวัฒนธรรม ประเพณี และงานศิลป์อันงดงามที่สืบทอดมายาวนาน นิทรรศการนี้จึงเป็นมากกว่าการจัดแสดงงานศิลปะ แต่คือบทสนทนาระหว่างสองมุมมอง ชวนให้ผู้ชมตั้งคำถามถึงวิถีชีวิตของตนเอง และค้นพบความงามในความแตกต่าง การหลอมรวม และการเรียนรู้ที่จะอยู่ร่วมกันอย่างกลมกลืน ในโลกที่เปลี่ยนแปลงไปอย่างรวดเร็วนี้ สุวรรณภูมิอาจเป็นคำตอบของการค้นหาความสงบและความงดงามในชีวิตผ่านสายตาและหัวใจของเหล่าศิลปินที่เชื่อมโยงอดีต ปัจจุบัน และอนาคตไว้ด้วยกันอย่างวิจิตร “สุวรรณภูมิ” จึงไม่ใช่เพียงแค่เรื่องราวในอดีต แต่คือความรุ่งเรืองของตำนานแห่งอารยธรรมของแผ่นดินทอง   RCB Galleria 2 ชั้น 2 ริเวอร์ ซิตี้ แบงค็อก",
    "categories": [
        "Art & Design",
        "Concert"
    ],
    "start_date": "9 เมษายน 2025",
    "end_date": "27 เมษายน 2025",
    "event_slot_time": "10:00–20:00",
    "location": "River City Bangkok",
    "url": "https://rivercitybangkok.com/th/%e0%b8%aa%e0%b8%b8%e0%b8%a7%e0%b8%a3%e0%b8%a3%e0%b8%93%e0%b8%a0%e0%b8%b9%e0%b8%a1%e0%b8%b4/",
    "ticket": "ไม่มีค่าเข้าชม",
    "ticket_price": null,
    "cover_picture": "https://rivercitybangkok.com/wp-content/uploads/fly-images/43802/Banner-Web-2880-x-944-01-1-1440x620-c.jpg",
    "reliability_score": 5,
    "timestamp": "2025-04-19 19:34:11",
    "status": "ongoing"
}