{
    "title": "Kite On The Lake",
    "description": "อิมแพ็คฯ เปิดตัวงานใหม่ริมทะเลสาบเมืองทอง “Kite on the Lake” เทศกาลว่าวถุงลมที่ใหญ่ และเยอะที่สุดในกรุงเทพ-ปริมณฑล กลางเดือนพ.ค.นี้ ถึงเวลาฮีลใจ ไม่ต้องไปไหนไกล เพราะอิมแพ็คฯเล่นใหญ่ จัดงาน “Kite on the Lake” อลังการกับว่าวถุงลมสีสันตระการตา มากกว่า 100 ตัว บนพื้นที่มากกว่า 3,000 ตารางเมตร เตรียมกล้องสุดโปรด และชุดตัวเก่งมาเช็คอินกับโลเคชั่นสุดปัง “ริมทะเลสาบเมืองทองธานี” พร้อมกิจกรรมให้คุณและครอบครัวได้ร่วมสนุก ไม่ว่าจะเป็น \n• การจัดแสดงว่าวไทย และนานาชาติ หลากหลายลวดลายกว่าหนึ่งร้อยตัว \n• กิจกรรม Workshop ระบายสี ประดิษฐ์ว่าว และอื่นๆ อีกมากมาย \n• ชมการแสดงดนตรีสด ภายใต้บรรยากาศสุดชิล ริมทะเลสาบ \n• “ช้อป ชิม ชิล” สินค้าเบ็ดเตล็ด อาหาร ของทานเล่น เครื่องดื่ม และคราฟท์เบียร์ กว่า 50 บูธ \n• Pet-friendly ยินดีต้อนรับน้องหมา น้องแมว และสัตว์เลี้ยงทุกสายพันธุ์ Kite on the Lake #เล่นว่าวริมเลค จัดยาวๆตลอด 3 วันเต็ม ตั้งแต่วันที่ 17 – 19 พฤษภาคมนี้ เวลา 16.00 – 22.00 น. @ริมทะเลสาบเมืองทอง งานนี้เข้างานฟรี จอดรถฟรี พร้อมบริการรถรับ-ส่ง ติดตามข่าวสาร ความเคลื่อนไหวของงานได้ที่  https://www.facebook.com/impactorganiser รายละเอียดเพิ่มเติม หรือสอบถามข้อมูล แอดไลน์ @impact.org หรือ  https://lin.ee/bZxw0aj",
    "categories": [
        "Food & Drink",
        "Others"
    ],
    "start_date": "17 พฤษภาคม 2024",
    "end_date": "19 พฤษภาคม 2024",
    "event_slot_time": "16:00 - 22:00",
    "location": "Impact IMPACT Lakeside",
    "url": "https://lin.ee/bZxw0aj",
    "ticket": "ไม่มีค่าเข้าชม",
    "ticket_price": null,
    "cover_picture": "null",
    "reliability_score": 5,
    "timestamp": "2025-05-07 16:23:43",
    "status": "past"
}