{
    "title": "LED Expo Thailand + SMARTECH ASEAN Online Networking & Knowledge Week",
    "description": "LED Expo Thailand + SMARTECH ASEAN Online Networking & Knowledge Week เดินหน้าจัดงานบนแพลตฟอร์มออนไลน์ พบกับกิจกรรมการจับคู่เจรจาธุรกิจเพื่อสร้างเครือข่ายและขยายโอกาสให้กับผู้ประกอบการด้านอุปกรณ์ส่องสว่างและระบบอัจฉริยะ และกิจกรรมสัมมนาความรู้ Knowledge Sessions & Conference โดยผู้เชี่ยวชาญที่มีชื่อเสียงจากหน่วยงานภาครัฐและเอกชนจากหลากหลายประเทศ โดยกิจกรรมสัมมนาความรู้ครอบคลุม 4 หัวข้อหลักคือ Energy Efficiency by Digitalization & Technology, Smart Lighting, IoT & Connectivity, Sustainability and Environment and Health & Wellbeing เพื่อเป็นแพลตฟอร์มแบ่งปันองค์ความรู้เชิงอุตสาหกรรม อีกทั้งช่วยเชื่อมต่อธุรกิจด้านแสงสว่างและระบบอัจฉริยะ IoT ด้วยการเจรจาธุรกิจระหว่างผู้ซื้อและผู้ขายจากทั่วโลก หากท่านต้องการเข้าร่วมเป็นวิทยากรหรือร่วมกิจกรรมเจรจาทางธุรกิจ สามารถติดต่อได้ที่  wishjanondv@impact.co.th แพลตฟอร์มออนไลน์:  www.ledexpothailand.com/knowledgeweek",
    "categories": [
        "Business",
        "Technology"
    ],
    "start_date": "14 กันยายน 2021",
    "end_date": "17 กันยายน 2021",
    "event_slot_time": "-",
    "location": "Impact Online Platform",
    "url": "http://www.ledexpothailand.com/knowledgeweek",
    "ticket": "ไม่มีค่าเข้าชม",
    "ticket_price": null,
    "cover_picture": "https://www.impact.co.th/userfiles/images/Event_calendar/2021/07-20-ledexpothailand-L.jpg",
    "reliability_score": 5,
    "timestamp": "2025-04-19 19:33:10",
    "status": "past"
}