{
    "title": "บางกอก อินเตอร์เนชั่นแนล มอเตอร์โชว์ ครั้งที่ 42",
    "description": "วิถีชีวิตใหม่ใจเป็นสุข \r\nจากวิกฤตการณ์โรคระบาดที่ส่งผลต่อ lifestyle ความเป็นอยู่และบทบาทหน้าที่ความรับผิดชอบต่าง ๆ ต่อสังคมอย่างเห็นได้ชัด ทำให้เกิดการพัฒนานวัตกรรมและเทคโนโลยีใหม่ ๆ เพื่อนำมาปรับใช้กับ พฤติกรรมในชีวิตประจำวันรวมถึงแนวคิด วิสัยทัศน์ การจัดการรักษา และฟื้นฟูเศรษฐกิจในประเทศ พัฒนา ปรับปรุง เรียนรู้ที่จะอยู่อย่างปลอดภัย และใช้ชีวิตอย่างเป็นสุข รอบวีไอพี 22 มีนาคม 2564 เวลา: 12:00-20:00 น. \r\nรอบสื่อมวลชน 23 มีนาคม 2564 เวลา: 09:59-18:00 น. \r\nรอบบุคคลทั่วไป 24 มีนาคม - 04 เมษายน 2564 \r\nจันทร์ - ศุกร์ เวลา: 12:00-22:00 น. \r\nเสาร์ - อาทิตย์ เวลา: 11:00-22:00 น.",
    "categories": [
        "Concert",
        "Others"
    ],
    "start_date": "24 มีนาคม 2021",
    "end_date": "04 เมษายน 2021",
    "event_slot_time": "Several Showtime",
    "location": "Impact Challenger 1-3",
    "url": "http://www.bangkok-motorshow.com",
    "ticket": "ไม่มีค่าเข้าชม",
    "ticket_price": null,
    "cover_picture": "https://www.impact.co.th/userfiles/images/Event_calendar/2021/02-19-42ndbangkokinternationalmotorshow2021-L.jpg",
    "reliability_score": 5,
    "timestamp": "2025-05-07 16:23:16",
    "status": "past"
}