{
  "title": "บันทึกลับ… ดอกเบญจมาศ",
  "description": "บันทึกลับ… ดอกเบญจมาศ\" คือนิทรรศการศิลปะที่เกิดจากการรวมตัวของศิลปินหญิง 5 ท่าน ผู้เปรียบเสมือนเพื่อน พี่ น้อง ที่เติบโตมากับเส้นทางศิลปะในแบบเฉพาะตน แม้จะมีแนวทางการสร้างสรรค์ที่แตกต่างกัน แต่กลับกลมกลืนได้อย่างลงตัวเมื่อนำมาจัดวางร่วมกันในพื้นที่เดียว เช่นเดียวกับ \"ดอกเบญจมาศ\" ที่มีหลายสี หลายรูปทรง แต่ยังคงคุณค่าในความงามและความหมาย ผลงานของศิลปินแต่ละคนก็สามารถเปรียบได้กับกลีบดอกไม้ที่ต่างกันแต่กลับกลมกลืนอยู่ในช่อเดียวกัน ก่อเกิดเป็นบทบันทึกลับแห่งความรู้สึก ความคิด และประสบการณ์ส่วนตัวที่ถ่ายทอดผ่านผลงานศิลปะหลากหลายรูปแบบ 🗓 ตั้งแต่วันที่ 2 - 18 พฤษภาคม 2568  📍ห้อง 249 ชั้น 2 ริเวอร์ ซิตี้ แบงค็อก",
  "start_date": "2 พฤษภาคม 2025",
  "end_date": "18 พฤษภาคม 2025",
  "categories": [
    "Art & Design",
    "Concert"
  ],
  "event_slot_time": "10:00-20:00",
  "location": "ริเวอร์ ซิตี้ แบงค็อก",
  "url": "https://www.bangkokartcity.org/th/discover-detail/secret-memoirs-of-the-chrysanthemum",
  "ticket": "ไม่มีค่าเข้าชม",
  "ticket_price": null,
  "cover_picture": "https://framerusercontent.com/images/FErrxhxREWHovC02k9qpDdYfddA.jpg",
  "reliability_score": 2,
  "timestamp": "2025-05-08 18:18:29",
  "status": "ongoing",
  "original_filename": "บันทึกลับ… ดอกเบญจมาศ.json"
}