{
  "title": "Food Pack Asia 2022",
  "description": "Food Pack Asia 2022 งานเดียวที่ให้ครบทุกเรื่องอุตสาหกรรมอาหาร เครื่องดื่ม บรรจุภัณฑ์ และโลจิสติกส์ อัดแน่นไปด้วยทัพเครื่องจักรอัตโนมัติ เครื่องจักรแปรรูปอาหาร เครื่องดื่ม และเครื่องจักรบรรจุภัณฑ์ รวมทั้งเทคโนโลยีและนวัตกรรมที่ทันสมัยต่างๆ มากมาย นอกจากนี้ยังมีธุรกิจ OEM รับจ้างผลิตอาหาร, เครื่องดื่ม, ยา, อาหารเสริม, สมุนไพร งานเดียวที่ช่วยติดปีกความสำเร็จสู่ธุรกิจคุณ",
  "categories": [
    "Food & Drink",
    "Business"
  ],
  "start_date": "4 เมษายน 2565",
  "end_date": "7 เมษายน 2565",
  "event_slot_time": " - ",
  "location": "Bitec Hall EH103",
  "url": "/cdn-cgi/l/email-protection#d7a7b8a5b9a4b6a0b6a3a197b0bab6bebbf9b4b8ba",
  "ticket": "ไม่มีค่าเข้าชม",
  "ticket_price": null,
  "cover_picture": "https://www.bitec.co.th/wp-content/uploads/2022/01/foodpack-1170x600-pix-01-1024x525.jpg",
  "reliability_score": 5,
  "timestamp": "2025-05-07 16:20:50",
  "status": "past",
  "original_filename": "854b2b37e127d218474b955192424156.json"
}