{
    "title": "Green Technology Expo 2024",
    "description": "งาน Green Technology Expo 2024 “เปิดประตูสู่อนาคต ” Driving Sustainable Solutions : Advancing Business Through Green Technology ส่งเสริมแผนงานความยั่งยืน ขับเคลื่อนธุรกิจด้วยเทคโนโลยีสีเขียว",
    "categories": [
        "Business",
        "Technology"
    ],
    "start_date": "24 ตุลาคม 2567",
    "end_date": "26 ตุลาคม 2567",
    "event_slot_time": "10:00 - 19:00",
    "location": "Bitec EH 101-102",
    "url": "https://www.bitec.co.th/th/event/green-technology-expo-2024",
    "ticket": "ไม่มีค่าเข้าชม",
    "ticket_price": null,
    "cover_picture": "https://www.bitec.co.th/wp-content/uploads/2024/04/Green-Technology-Expo-2024-1170x600-2-1024x525.jpg",
    "reliability_score": 5,
    "timestamp": "2025-05-07 16:22:03",
    "status": "past"
}