{
    "title": "Intelligent Asia Thailand 2025",
    "description": "8 March 2025 10:00 – 17:00",
    "categories": [
        "Others",
        "Concert"
    ],
    "start_date": "6 มีนาคม 2568",
    "end_date": "8 มีนาคม 2568",
    "event_slot_time": "10:00 - 18:00",
    "location": "Bitec EH 102 – 103",
    "url": "https://www.facebook.com/profile.php?id=61554134360001",
    "ticket": "ไม่มีค่าเข้าชม",
    "ticket_price": null,
    "cover_picture": "https://www.bitec.co.th/wp-content/uploads/2025/01/【IAT】BITEC-Banner_1.1170X600-1024x525.jpg",
    "reliability_score": 5,
    "timestamp": "2025-03-29 17:13:04",
    "status": "past"
}