{
    "title": "METALEX 2022",
    "description": "No. 1 Machine Tools & Metalworking Exhibition Serving ASEAN – 36th Edition METALEX 2022 will pave the way to sustainable successes in the imminent 4.0 era for the region’s metalworking industry. The show will open up new horizons in metalworking excellence and growth through over 4,800 items of new machine tools, metalworking solutions, sheet metal forming innovations, and many other metalworking technologies by 4,000 brands from 50 countries as well as many other exciting smart new features, contents, and business opportunities that will take your business to the next level. METALEX will be your smart gateway that will enable you to tap into the demanding ASEAN market in the most efficient and effective way.",
    "categories": [
        "Technology",
        "Concert"
    ],
    "start_date": "16 พฤศจิกายน 2565",
    "end_date": "19 พฤศจิกายน 2565",
    "event_slot_time": " - ",
    "location": "null",
    "url": "https://www.bitec.co.th/th/event/metalex-2022",
    "ticket": "ไม่มีค่าเข้าชม",
    "ticket_price": null,
    "cover_picture": "https://www.bitec.co.th/wp-content/uploads/2021/11/MTX_BANNER.jpg",
    "reliability_score": 5,
    "timestamp": "2025-05-07 16:21:05",
    "status": "past"
}