{
    "title": "Nova BUILD EXPO 2023",
    "description": "งานมหกรรมการแสดงนวัตกรรมอาคารและความคิดสร้างสรรค์เสริมสร้างความสุขและความปลอดภัยของชีวิต เพื่อสิ่งแวดล้อมและโลกที่ยั่งยืน",
    "categories": [
        "Business",
        "Technology"
    ],
    "start_date": "13 กันยายน 2566",
    "end_date": "15 กันยายน 2566",
    "event_slot_time": "10:00 - 18:00",
    "location": "Bitec ฮอลล์ EH 103-104",
    "url": "http://nova-build.com/?fbclid=IwAR0u-s1s_ZwBJnd4oTqzO79svP7-CotQRg4AxjaBPKwNgQ0WVpSz-HjwAtM",
    "ticket": "ไม่มีค่าเข้าชม",
    "ticket_price": null,
    "cover_picture": "https://www.bitec.co.th/wp-content/uploads/2023/06/1170x600px_EN-1024x525.jpg",
    "reliability_score": 5,
    "timestamp": "2025-05-07 16:21:30",
    "status": "past"
}