{
    "title": "เมทัลเล็กซ์ 2024",
    "description": "นักอุตสาหกรรมโลหการจำนวนกว่า 100,000 คนจะได้ก้าวสู่ความเป็นผู้นำของวงการเมื่อได้พบการเปิดตัวของนวัตกรรมแห่งเครื่องจักรกลและเทคโนโลยีโลหการใหม่ในงานเมทัลเล็กซ์ ที่ซึ่งผู้ผลิตและผู้จำหน่ายเทคโนโลยีกว่า 3,000 แบรนด์จากทั่วทุกมุมโลก รวมทั้งผู้จำหน่าย Smart Materials และเทคโนโลยี AI จะมาร่วมกันเปิดตัวเทคโนโลยีใหม่ที่จะนำประสิทธิภาพและความสามารถในการผลิตอีกขั้นมาให้กับผู้ประกอบการจากทั่วอาเซียน",
    "categories": [
        "Concert",
        "Book"
    ],
    "start_date": "20 พฤศจิกายน 2567",
    "end_date": "23 พฤศจิกายน 2567",
    "event_slot_time": "10:00 - 18:00",
    "location": "Bitec ฮอลล์ EH98-104",
    "url": "https://www.bitec.co.th/th/event/%e0%b9%80%e0%b8%a1%e0%b8%97%e0%b8%b1%e0%b8%a5%e0%b9%80%e0%b8%a5%e0%b9%87%e0%b8%81%e0%b8%8b%e0%b9%8c-2024",
    "ticket": "ไม่มีค่าเข้าชม",
    "ticket_price": null,
    "cover_picture": "https://www.bitec.co.th/wp-content/uploads/2024/01/METALEX-2024-1170x600-2-1024x525.jpg",
    "reliability_score": 5,
    "timestamp": "2025-05-07 16:22:07",
    "status": "past"
}