{
  "title": "งานเทศกาลบุฟเฟ่ต์ทุเรียน DURIAN PARADISE \"All You Can Eat\" ",
  "description": "งานเทศกาลบุฟเฟ่ต์ทุเรียน DURIAN PARADISE \"All You Can Eat\" พบกับบุฟเฟ่ต์ทุเรียน จัดหนัก จัดเต็ม ราคาเริ่มต้นที่ 699 บาท อร่อยสะใจกับทุเรียนหลากหลายสายพันธุ์ให้ทุกคนได้ลิ้มลอง คัดสรรทุเรียนพันธุ์ยอดนิมยม และ พันธุ์หายาก รวมถึงผลไม้เกรดพรี เมี่ยม จาก Queen Frozen Fruit เลือกอร่อยแบบไม่อั้นได้ในราคาสุดคุ้มค่า มี 3 ราคาให้เลือก พร้อมเครื่องดื่ม ของหวานและผลไม้ตามฤดูกาลแบบไม่อั้น!Standard Durian Buffet ราคา 699 (จำกัดเวลาทาน 60 นาที) สายพันธุ์ที่ทานได้: หมอนทอง, พวงมณีPremium Durian Buffet ราคา 1,099 (จำกัดเวลาทาน 60 นาที) สายพันธุ์ที่ทานได้: หมอนทอง, พวงมณี, ก้านยาว, นกหยิบVIP Experience Durian Buffet ราคา 1,399 (จำกัดเวลาทาน 60 นาที) สายพันธุ์ที่ทานได้: หมอนทอง, พวงมณี, ก้านยาว, นกหยิบ, มูซานคิงส์, หลงลับแล และ ทองหลินจงทุกราคาสามารถทาน เครื่องดื่ม ผลไม้ตามฤดูกาล และของหวานจากทุเรียนของหวานจากทุเรียน: ไอศกรีมทุเรียน, ลาซานญ่าทุเรียน (อบร้อน), ข้าวเหนียวทุเรียนผลไม้: มังคุด, เงาะเครื่องดื่ม: น้ำมะพร้าวสด, น้ำเปล่าเปิดวันละ 5 รอบ รอบละ 1 ชั่วโมง 10.00 - 11.00 น. / 12.00 - 13.00 น. / 14.00 - 15.00 น. / 16.00 - 17.00 น./ 18.00 - 19.00 น.วันที่ 24 เมษายน - 1 พฤษภาคม 2568เวลา 10:00 - 19:00 น.ลาน Common Space ชั้น G โครงการฟีนิกซ์ ประตูน้ำ",
  "categories": [
    "Others",
    "Concert"
  ],
  "start_date": "24 เมษายน 2025",
  "end_date": "1 พฤษภาคม 2025",
  "event_slot_time": null,
  "location": "ฟีนิกซ์ - Phenix",
  "url": "https://www.facebook.com/PhenixFoodWholesaleHub",
  "cover_picture": "https://api.thailandexhibition.com/uploads/24_9_DURIAN_PARADISE_All_You_Can_Eat_85340bf55d.jpg",
  "ticket": "มีค่าเข้าชม",
  "ticket_price": [
    699,
    699,
    1099,
    1399
  ],
  "reliability_score": 2,
  "timestamp": "2025-05-07 16:25:12",
  "status": "past",
  "original_filename": "185350ded1cb741b11f0aee49ba4a76a.json"
}