{
  "title": "\"Nice to Meet You\" Group Exhibition",
  "description": "\"Nice to Meet You\" Group Exhibitionวันที่ 2 - 14 มีนาคม 2568ณ ชั้น 2 Art4C Art Centre“ก๊อก ๆ สวัสดี ยินดีที่ได้รู้จัก!” มา “ทำความรู้จัก” กับพวกเราเป็นครั้งแรก เหล่าตัวละครสุดน่ารัก โดยศิลปินทั้ง 5 คน ผ่านเรื่องราวในฤดูอันหลากหลาย เหมือนกับนิสัยและจิตใจที่แตกต่างกันออกไปของแต่ละคน! โดย 5 ศิลปินกมลชนก มณีไพโรจน์จิณณณัฏฐ์ น้าประเสริฐพิมพ์กานต์ นพคุณนิพิษฐา วันพนมดนยา ตันปัทมดิลกExhibition Duration: March 2 - 14, 2025Time: 10 AM - 7 PM (Closed on Monday)Location: 2nd Floors, Art4C Art Centre (https://maps.app.goo.gl/dRcnkAyNLxYEYCyC7)",
  "categories": [
    "Art & Design",
    "Concert"
  ],
  "start_date": "2 มีนาคม 2025",
  "end_date": "14 มีนาคม 2025",
  "event_slot_time": "10:00–19:00",
  "location": "Art4C Art Centre",
  "url": "https://www.facebook.com/art4c.artcentre",
  "cover_picture": "https://api.thailandexhibition.com/uploads/Nice_to_Meet_You_Group_Exhibition_2487d6b8c6.jpg",
  "ticket": "ไม่มีค่าเข้าชม",
  "ticket_price": null,
  "reliability_score": 2,
  "timestamp": "2025-05-07 16:25:07",
  "status": "past",
  "original_filename": "3dc56f8cc0a2ddc4e8fcb1076984a80c.json"
}