{
  "title": "DRIVEN ",
  "description": "สตาร์ทขุมพลังแรงขับเคลื่อน และเตรียมพบกับการประมูล และนิทรรศการแสดงผลงานศิลปะสุดยิ่งใหญ่ของ The Art Auction Center บริษัทประมูลศิลปะอันดับ 1 ของไทย กับ “DRIVEN”DRIVEN นิทรรศการที่สร้างสรรค์ให้เป็นดั่งพาหนะชั้นเยี่ยมที่จะนำพาทุกๆท่านพุ่งทะยานไปสัมผัสประกายไฟแห่งพลังและจิตวิญญาณของศิลปินผ่านผลงานกว่า 133 ชิ้น ที่จัดแสดงควบคู่ไปกับสุดยอดยนตรกรรมจาก 911 Assistant ศูนย์ให้บริการ รถยนต์ Porsche ชั้นแนวหน้าของประเทศ เพื่อร่วมเดินทางไปสู่จุดหมายปลายทางอันเกินขอบเขตของจิตนาการร่วมกันAuction Preview 21- 24 November 2024 11.00 - 20.00 hrs. At River City Bangkok,RCB Artery (1st floor) and RCB Galleria 4 (2nd floor)Auction Date 24 November 2024 - Auction starts at 14.00 hrs. At River City Bangkok",
  "categories": [
    "Art & Design",
    "Concert"
  ],
  "start_date": "21 พฤศจิกายน 2024",
  "end_date": "24 พฤศจิกายน 2024",
  "event_slot_time": null,
  "location": "ริเวอร์ ซิตี้ แบงค็อก - River City Bangkok",
  "url": "https://www.facebook.com/theartauctioncenter",
  "cover_picture": "https://api.thailandexhibition.com/uploads/18_6_Auction_Preview_1e6a184ffc.jpg",
  "ticket": "ไม่มีค่าเข้าชม",
  "ticket_price": null,
  "reliability_score": 2,
  "timestamp": "2025-05-07 16:24:54",
  "status": "past",
  "original_filename": "DRIVEN .json"
}