{
  "title": "Music in the Garden",
  "description": "Music in the Gardenวันที่ 25 พฤศจิกายน - 20 ธันวาคม 2567เวลา 17.00 - 24.00 น.ณ The PARQ, ลาน Q Spaceเทศกาลแห่งความสุขเคล้าเสียงดนตรีเวียนกลับมาอีกครั้ง ชวนมาชิลหลังเลิกงานที่ Chang Live Park ลาน Q Space พร้อมชมคอนเสิร์ตจากศิลปินชื่อดังมากมาย ที่จะเวียนมาสร้างความบันเทิงตลอดการจัดงาน อาทิส้ม มารี (11 ธ.ค.)โอ๊ต ปราโมทย์ (12 ธ.ค.)สงกรานต์ (13 ธ.ค.)ลุลา(วันเสาร์ที่ 14 ธ.ค.)กวาง AB Normal (วันอาทิตย์ที่ 15 ธ.ค.)Purpeech (16 ธ.ค.)Yourmood (17 ธ.ค.)Only Monday (18 ธ.ค.)Blackbeans (19 ธ.ค.)60 Miles (20 ธ.ค.)มาเติมเต็มช่วงเวลาแห่งความสุขส่งท้ายปีกันได้ ตั้งแต่วันที่ 25 พฤศจิกายน - 20 ธันวาคม 2567 (ยกเว้นวันเสาร์อาทิตย์และวันหยุดนักขัตฤกษ์) *จำกัดเฉพาะผู้มีอายุ 20 ปีขึ้นไปสำหรับคอนเสิร์ตจากศิลปินเริ่มสำรองโต๊ะได้ตั้งแต่วันที่ 27 พฤศจิกายน 2567 เป็นต้นไป สำรองโต๊ะผ่านทาง Website ชงเจริญ เท่านั้น https://chongjaroen.com/event",
  "categories": [
    "Concert",
    "Art & Design"
  ],
  "start_date": "25 พฤศจิกายน 2024",
  "end_date": "20 ธันวาคม 2024",
  "event_slot_time": null,
  "location": "เดอะ ปาร์ค - The PARQ",
  "url": "https://www.facebook.com/theparqbkk",
  "cover_picture": "https://api.thailandexhibition.com/uploads/Music_in_the_Garden_05588e620f.jpg",
  "ticket": "ไม่มีค่าเข้าชม",
  "ticket_price": null,
  "reliability_score": 2,
  "timestamp": "2025-05-07 16:24:55",
  "status": "past",
  "original_filename": "7327d5bccb1b6b4b417284bf83ce0b99.json"
}