{
    "title": "Art is a Start by Arttitude",
    "description": "Art is a Start by Arttitudeวันที่ 4 สิงหาคม - 14 สิงหาคม 2567ณ ชั้น 3 Art4C Art Centre“Art is a Start by Arttitude” นิทรรศการส่งเสริมศิลปะบำบัดที่นำเสนอผลงานของผู้เข้าร่วมกิจกรรม เพื่อสร้างความตระหนักรู้ถึงความสำคัญของสุขภาพใจ และแบ่งปันเทคนิคง่ายๆที่นำไปใช้ได้ในชิวิตประจำวันเพื่อดูแลจิตใจตัวเองและคนรอบข้างจัดโดย อาร์ตติจูด (@arttitude.world) โครงการจิตอาสาที่ถูกก่อตั้งโดยเยาวชน เพื่อส่งเสริมศิลปะบำบัดให้ทุกคนเข้าถึงได้ง่ายขึ้น โดยการผสมผสานเวิร์กช็อปแบบลงพื้นที่และวิดีโอสอนออนไลน์อาร์ตติจูดขอเชิญชวนทุกท่านมาศึกษาจิตใจตัวเอง เรียนรู้เกี่ยวกับศิลปะบำบัด และให้เราเป็นจุดเริ่มต้นในการดูแลจิตใจของคุณ เปิดนิทรรศการในวันที่ 4 สิงหาคม 2567 เวลา 15.00 น. เป็นต้นไปจัดขึ้นระหว่างวันที่ 4 สิงหาคม - 14 สิงหาคม 2567 (ปิดทุกวันจันทร์)เวลา 10.00 - 19.00 น. ณ ชั้น 3, Art4C Art Centre",
    "categories": [
        "Art & Design"
    ],
    "start_date": "4 สิงหาคม 2024",
    "end_date": "14 สิงหาคม 2024",
    "event_slot_time": "10:00–19:00",
    "location": "Art4C Art Centre",
    "url": "https://www.facebook.com/art4c.artcentre",
    "cover_picture": "https://api.thailandexhibition.com/uploads/Art_is_a_Start_by_Arttitude_5f36befa9a.jpg",
    "ticket": "ไม่มีค่าเข้าชม",
    "ticket_price": null,
    "reliability_score": 2,
    "timestamp": "2025-04-19 19:34:49",
    "status": "past"
}