{
    "title": "Unlock Your iPhone's Creative Potential",
    "description": "เตรียมพบกับ Workshop รับ Grand Opening  ร้าน iStudio Terminal 21 Asok โฉมใหม่ที่จะมาทำให้คุณใช้ iPhone ได้ครีเอทีฟมากยิ่งขึ้น! ในหัวข้อ Unlock Your iPhone's Creative Potential ปลดล็อกศักยภาพการสร้างสรรค์ด้วย iPhone ของคุณหัวข้อที่น่าสนใจแนะนำการตั้งค่ากล้อง iPhone ขั้นพื้นฐานยกระดับการถ่ายภาพให้ดูโปรมากยิ่งขึ้นเรียนรู้เทคนิคการแต่งรูปมืออาชีพด้วยแอปยอดนิยมกับวิทยากรพิเศษ คุณ มด ศิลา พีรวัฑฒึก (TikToker and influencers) พ่อมด TikTok ชื่อดัง ! เอเนอร์จี้เกิน 100 วันที่ 14 กันยายน 2567 เวลา 14.00 - 16.00 น.iStudio by UFicon สาขา Terminal 21 Asok ชั้น 1ลงทะเบียนฟรี สำรองที่นั่งก่อนใคร www.uficon.com/workshop/register2",
    "categories": [
        "Education",
        "Others"
    ],
    "start_date": "14 กันยายน 2024",
    "end_date": "14 กันยายน 2024",
    "event_slot_time": null,
    "location": "เทอร์มินอล21 อโศก - Terminal21 Asok",
    "url": "https://www.facebook.com/istudiobyuficon",
    "cover_picture": "https://api.thailandexhibition.com/uploads/27_10_Unlock_Your_i_Phone_s_Creative_Potential_e476aef302.jpg",
    "ticket": "ไม่มีค่าเข้าชม",
    "ticket_price": null,
    "reliability_score": 2,
    "timestamp": "2025-05-07 16:24:44",
    "status": "past"
}