{
    "title": "Winter Wonderland",
    "description": "Winter Wonderlandวันที่ 24 ธันวาคม 2567 - 5 มกราคม 2568ณ ลานกิจกรรมชั้น 1 โซนลิฟต์แก้ว เซ็นทรัล ปิ่นเกล้าต้อนรับลมหนาวกลางกรุง พบกับ Winter Wonderland สัมผัสความหนาวแบบฟิน ๆ กับลานหิมะกลางศูนย์การค้า",
    "categories": [
        "Art & Design",
        "Others"
    ],
    "start_date": "24 ธันวาคม 2024",
    "end_date": "5 มกราคม 2025",
    "event_slot_time": null,
    "location": "เซ็นทรัล ปิ่นเกล้า - Central Pinklao",
    "url": "https://www.facebook.com/CentralPinklaoFanpage",
    "cover_picture": "https://api.thailandexhibition.com/uploads/Winter_Wonderland_4d75b220f0.jpg",
    "ticket": "ไม่มีค่าเข้าชม",
    "ticket_price": null,
    "reliability_score": 2,
    "timestamp": "2025-03-29 17:15:57",
    "status": "past"
}