{
    "title": "THE CORRS LIVE IN BANGKOK",
    "description": "ความสุขจากบทเพลงที่คุ้นเคยจากยุค 90s และ 2000 กำลังหวนกลับมาทำให้หัวใจคุณชื่นฉ่ำอีกครั้ง กับ THE CORRS ตำนานป็อปจากไอริชกับทัวร์ ‘Talk on Corners’ In Thailand ต้อนรับเดือนแห่งความรัก THE CORRS LIVE IN BANGKOK วันที่ 11 กุมภาพันธ์ 2568 พารากอน ฮอลล์ ชั้น 5 สยามพารากอน บัตร 2,000 / 3,500 / 4,000 / 5,000 / 6,500 บาท จำหน่ายบัตรทาง Thaiticketmajor: ...",
    "categories": [
        "Concert"
    ],
    "start_date": "11 กุมภาพันธ์ 2025",
    "end_date": "11 กุมภาพันธ์ 2025",
    "event_slot_time": "20:00 - 22:00",
    "location": "Paragon Hall, NORTH + SOUTH HALL",
    "url": "mailto:sales@paragonhall.com",
    "ticket": "มีค่าเข้าชม",
    "ticket_price": [
        3500,
        4000,
        5000,
        6500
    ],
    "cover_picture": "https://d2hgly9q1uujdd.cloudfront.net/media/content/2025/01/27/11/4990/1737976818.1134.jpg",
    "reliability_score": 5,
    "timestamp": "2025-04-19 19:34:02",
    "status": "past"
}