{
  "title": "Goes on",
  "description": "โดย คณะศิลปกรรมศาสตร์ จุฬาลงกรณ์มหาวิทยาลัย นิทรรศการแสดงงานศิลปะเป็นอีกหนึ่งช่องทางให้ผลงานของศิลปินรุ่นใหม่ได้ถูกนำเสนอต่อสาธารณชน เป็นการขยายเผยแพร่วงการศิลปะให้กว้างขวางขึ้น และเปิดโอกาสให้เหล่าศิลปินรุ่นใหม่ได้แสดงออกถึงความคิดสร้างสรรค์ของตนเองออกมาผ่านงานศิลปะ นิทรรศการศิลปนิพนธ์ “ Goes on “ นี้เป็นนิทรรศการแสดงผลงานศิลปนิพนธ์ของนิสิตคณะศิลปกรรมศาสตร์ ภาควิชา ทัศนศิลป์ จุฬาลงกรณ์มหาวิทยาลัยรุ่นที่ 37 เป็นการรวมตัวกันของนิสิตทั้งหมด 31 คนใน 4 สาขา ประกอบด้วย จิตรกรรม ภาพพิมพ์ ประติมากรรม และภาพถ่าย นิทรรศการนี้มีจุดประสงค์ที่ต้องการสื่อให้เห็นถึงชิ้นงานของนิสิตที่แต่ละคนที่มีแนวทางเป็นของตนเอง ดังนั้นจึงยกคำว่า Go on มาใช้  โดย Go on หรือ goes on เป็น phrasal verb ที่ไปกับคำว่า go ที่เป็น verb ความหมายของมันคือ to happen หรือ to continue   Goes on ใช้ในโอกาสที่พูดถึงสิ่งที่ต่อเนื่องไปในอนาคต เรามักจะเห็นการใช้คำว่า goes on กับคำว่า life goes on  ดังนั้น นิทรรศการนี้ต้องการกล่าวถึง การไปต่อของทุก ๆ คน ที่ไม่ได้หมายถึงแค่เพียงการเรียนจบ แต่หมายถึงชีวิตของแต่ละคนที่ต้องเดินต่อไปในอนาคต สอบถามรายละเอียดเพิ่มเติมได้ที่ คุณศตายุ ลิ่วกิตติวรกุล โทร. 06-3234-9651 Instagram Visualarts.cu",
  "categories": [
    "Art & Design",
    "Concert"
  ],
  "start_date": "27 มิถุนายน 2023",
  "end_date": "1 กรกฎาคม 2023",
  "event_slot_time": "10.00-20.00",
  "location": "BACC สถานที่ผนังโค้ง ชั้น 3ผนังโค้ง ชั้น 4ผนังโค้ง ชั้น 5",
  "url": "https://www.bacc.or.th/events/13644",
  "ticket": "ไม่มีค่าเข้าชม",
  "ticket_price": null,
  "cover_picture": "https://www.bacc.or.th/wp-content/uploads/2023/06/GOESON_500x738px-1.jpg",
  "reliability_score": 5,
  "timestamp": "2025-05-07 16:16:41",
  "status": "past",
  "original_filename": "6abbbb74deca3938621c3624553b9bad.json"
}