{
  "title": "BACC Art Trail ‘Bangkok 242 : A Space for Sharing’",
  "description": "โดย หอศิลปวัฒนธรรมแห่งกรุงเทพมหานคร หอศิลปกรุงเทพฯ เชิญชวนทุกคนมาร่วมสนุกไปกับ ‘BACC Art Trail’นิทรรศการ ‘Bangkok 242 : A Space for Sharing’ ใบงานกิจกรรม (Activity Guide) ประกอบนิทรรศการ ‘กรุงเทพฯ ๒๔๒’ ณ ห้องนิทรรศการหลัก ชั้น 8 หอศิลปกรุงเทพฯ ที่จะช่วยเปลี่ยนประสบการณ์การชมนิทรรศการศิลปะของทุกคนให้กลายเป็นช่วงเวลาแห่งการพักผ่อนที่ทั้งสนุกและได้ความรู้ โดยสามารถร่วมทำ ‘BACC Art Trail’ จะทำหน้าที่เสมือนเพื่อนชวนคุยระหว่างการชมนิทรรศการ ด้วยชุดคำถามแบบง่ายที่ตั้งใจออกแบบเพื่อการเรียนรู้ด้านศิลปะสำหรับทุกคน * สามารถรับ BACC Art Trail ได้ตั้งแต่วันนี้ – 19 พฤษภาคม 2567 ณ บริเวณหน้าห้องนิทรรศการหลัก ชั้น 8 ** ฟรี! ไม่มีค่าใช้จ่าย ดาวน์โหลด BACC Art Trail ‘Bangkok 242 : A Space for Sharing’ คลิก (https://www.bacc.or.th/upload_2/bkk242_trail_online_(1).pdf)",
  "categories": [
    "Art & Design"
  ],
  "start_date": "8 เมษายน 2024",
  "end_date": "19 พฤษภาคม 2024",
  "event_slot_time": "10.00-20.00",
  "location": "BACC สถานที่ห้องนิทรรศการหลัก ชั้น 8",
  "url": "https://www.bacc.or.th/events/78020",
  "ticket": "ไม่มีค่าเข้าชม",
  "ticket_price": null,
  "cover_picture": "null",
  "reliability_score": 5,
  "timestamp": "2025-05-07 16:15:24",
  "status": "past",
  "original_filename": "BACC Art Trail ‘Bangkok 242 _ A Space for Sharing’.json"
}