{
    "title": "Level UP Art Thesis Exhibition",
    "description": "โดย สาขาวิชาออกแบบนิเทศศิลป์ วิทยาลัยเพาะช่าง พิธีเปิด 19 มีนาคม 2564 เวลา 11.00 น. นิทรรศการศิลปนิพนธ์ Level UP Art Thesis Exhibition โดยนักศึกษา ชั้นปีที่4  สาขาวิชาออกเเบบนิเทศศิลป์ ภาควิชาออกแบบ วิทยาลัยเพาะช่าง มหาวิทยาลัยเทคโนโลยีราชมงคลรัตนโกสินทร์ จัดเเสดงผลงาน วันที่ 19-21 มีนาคม 2564 เวลา 11.00-19.00 น. ณ ชั้น L หอศิลปวัฒนธรรมแห่งกรุงเทพมหานคร (bacc) สอบถามข้อมูลเพิ่มเติมได้ที่ นาย ธวัชชัย คำสีทา โทร 095-9145921 Facebook: Level UP Art Thesis Exhibition 2021 (https://www.facebook.com/Level-UP-Art-Thesis-Exhibition-2021-105511567707276)",
    "categories": [
        "Art & Design"
    ],
    "start_date": "19 มีนาคม 2021",
    "end_date": "20 มีนาคม 2021",
    "event_slot_time": "10.00-20.00",
    "location": "BACC สถานที่โถง ชั้น L",
    "url": "https://www.bacc.or.th/events/12428",
    "ticket": "ไม่มีค่าเข้าชม",
    "ticket_price": null,
    "cover_picture": "https://www.bacc.or.th/wp-content/uploads/2021/03/Poster-scaled.jpg",
    "reliability_score": 5,
    "timestamp": "2025-03-29 17:09:43",
    "status": "past"
}