{
    "title": "Shadow Collective",
    "description": "โดย Little Rocket ร่วมกับ กรุงเทพมหานคร เวลา: 13:30 – 16:30 Little Rocket ร่วมกับ กรุงเทพมหานคร และ อาสาสมัครกลุ่มมะขามป้อม ขอชวนทุกคนมาเรียนรู้ Diversity แบบ Non-verbal ผ่านชุดความคิดและความรู้สึกของตัวเอง กับ… 'Shadow Collective: ละครเงาเพื่อหาพื้นที่ให้ความแตกต่าง ' จากอาสาสมัครกลุ่มมะขามป้อม ! Shadow Collective คืออะไร ? ชุดแบบฝึกหัดที่ใช้กระบวนการละครผ่านแสงและเงา เข้ามาทดลองการโต้ตอบที่อาจเกิดขึ้นในชีวิตจริง เพื่อเรียนรู้และทำความเข้าใจความแตกต่าง ความขัดแย้ง และความเป็นมนุษย์ ค่าใช้จ่าย : 399 บาทเท่านั้น! (รวมของว่าง อุปกรณ์ และสนับสนุน Community)​ หากสนใจลงทะเบียน https://forms.gle/YSqWeE3YQoWxKHaB8 เพียงตอบคำถามในแบบฟอร์มพร้อมแนบสลิปโอนเงิน **จำกัดจำนวนที่นั่ง 15 ที่เท่านั้น* (First come, First serve ตามคนที่โอนเงินเข้ามาก่อน) (https://docs.google.com/forms/d/e/1FAIpQLScqg0dUjOKBJ9uT56rsq8ivV7NObyQ9c3ApPBmX9R0lzI4mvg/viewform?usp=send_form) สอบถามรายละเอียดเพิ่มเติมได้ที่ คุณเซป โทร. 081-4533844 Facebook: Little Rocket : พื้นที่เรียนรู้ผ่านการแบ่งปัน Instagram: @littlerocketofficial__ (https://web.facebook.com/littlerocketcommunity/)",
    "categories": [
        "Art & Design"
    ],
    "start_date": "19 พฤศจิกายน 2022",
    "end_date": "19 พฤศจิกายน 2022",
    "event_slot_time": "10.00-20.00",
    "location": "BACC สถานที่ห้องประชุม ห้อง 501 ชั้น 5",
    "url": "https://www.bacc.or.th/events/13461",
    "ticket": "มีค่าเข้าชม",
    "ticket_price": [
        399
    ],
    "cover_picture": "https://www.bacc.or.th/wp-content/uploads/2022/11/03.1_Website_Thumbnail_20221119.jpg",
    "reliability_score": 5,
    "timestamp": "2025-03-29 17:08:27",
    "status": "past"
}