{
    "title": "World Mental Health Day 2022 – Better Mind, Better Bangkok",
    "description": "โดย มูลนิธิสติแอพ ร่วมกับ เครือข่ายสุขภาพจิตภาคประชาชน เนื่องด้วยวันที่ 10 ตุลาคม ของทุกปีเป็นวันสุขภาพจิตโลก หรือ World Mental Health Day มีจุดมุ่งหมายให้ประชากรทั่วโลกได้เห็นความสำคัญของสุขภาพจิตและการลงทุนเพื่อการป้องกันและบำบัดรักษาผู้ที่เจ็บป่วยทางจิตใจ ทางเครือข่ายสุขภาพจิตภาคประชาชน ได้แก่ มูลนิธิสติแอพ (ผู้ประสานหลักโครงการ) มูลนิธิรุกข์ กลุ่ม Understand และเครือข่าย Global Shapers Bangkok เป็นต้น ได้เล็งเห็นความสำคัญของการจัดกิจกรรมที่มีจุดมุ่งหมายในการสร้างความตระหนักและการสร้างพลังใจเพื่อรับมือกับผลกระทบด้านสุขภาพจิตที่กำลังเพิ่มมากขึ้นของคนเมืองโดยเฉพาะประชาชนในเขตกรุงเทพมหานคร ทางเครือข่ายสุขภาพจิตภาคประชาชน จึงมีแนวคิดริเริ่มในการจัดงาน “วันสุขภาพจิตโลก – Better Mind, Better Bangkok” ขึ้นเป็นครั้งแรก ในวันอาทิตย์ที่ 9 ตุลาคม 2565 ณ หอประชุม ชั้น5  หอศิลปวัฒนธรรมแห่งกรุงเทพมหานคร เขตปทุมวัน กรุงเทพมหานคร สามารถลงทะเบียนได้ คลิก เปิดรับลงทะเบียนตั้งแต่วันนี้- 8 ตุลาคม 2565 (https://book.soldoutt.com/better-mind-better-bangkok/register) สอบถามรายละเอียดเพิ่มเติมได้ที่ คุณอมรเทพ สัจจะมุนีวงศ์ (ผู้ก่อตั้งมูลนิธิ สติแอพ) โทร. 08 6 -545-3465 Facebook Sati App (https://www.facebook.com/satiapp)",
    "categories": [
        "Concert",
        "Others"
    ],
    "start_date": "9 ตุลาคม 2022",
    "end_date": "9 ตุลาคม 2022",
    "event_slot_time": "10.00-20.00",
    "location": "BACC สถานที่ห้องออดิทอเรียม ชั้น 5",
    "url": "https://www.bacc.or.th/events/13438",
    "ticket": "ไม่มีค่าเข้าชม",
    "ticket_price": null,
    "cover_picture": "https://www.bacc.or.th/wp-content/uploads/2022/10/500_738-scaled.jpg",
    "reliability_score": 5,
    "timestamp": "2025-04-19 19:24:33",
    "status": "past"
}